medor/__about__.py
medor/__init__.py
medor/medor.py
medor/utils/__init__.py
medor/utils/bone.py
medor/utils/net.py
medor/utils/tor.py
medor/utils/uas.py
medor/utils/util.py
medor-0.1.3.dist-info/METADATA
medor-0.1.3.dist-info/WHEEL
medor-0.1.3.dist-info/entry_points.txt
medor-0.1.3.dist-info/licenses/LICENSE
medor-0.1.3.dist-info/RECORD
