Metadata-Version: 2.3
Name: medor
Version: 0.1.3
Summary: medor is an OSINT tool that enables you to discover a WordPress website IP behind a WAF or behind Onion Services.
Project-URL: Homepage, https://github.com/balestek/medor
Project-URL: Bug Tracker, https://github.com/balestek/medor/issues
Author: balestek
License:                     GNU GENERAL PUBLIC LICENSE
License-File: LICENSE
Keywords: darknet,information-gathering,investigation,onion,onion-service,open-source-intelligence,osint,osint-python,osint-tool,osint-tools,pingback,pipenv,pypi,python,wordpress,wordpress-osint,wp-osint,xml-rpc,xmlrpc
Classifier: Development Status :: 4 - Beta
Classifier: Environment :: Console
Classifier: License :: OSI Approved :: GNU General Public License v3 (GPLv3)
Classifier: Natural Language :: English
Classifier: Operating System :: OS Independent
Classifier: Programming Language :: Python :: 3
Classifier: Programming Language :: Python :: 3.8
Classifier: Programming Language :: Python :: 3.9
Classifier: Programming Language :: Python :: 3.10
Classifier: Programming Language :: Python :: 3.11
Classifier: Programming Language :: Python :: 3.12
Requires-Python: >=3.8
Requires-Dist: beautifulsoup4
Requires-Dist: brotlipy
Requires-Dist: colorama
Requires-Dist: docopt
Requires-Dist: halo
Requires-Dist: httpx
Requires-Dist: httpx[socks]
Requires-Dist: lxml
Requires-Dist: python-dotenv
Requires-Dist: stem
Requires-Dist: validators
